README.md
setup.cfg
setup.py
gym_armed_bandits/__init__.py
gym_armed_bandits.egg-info/PKG-INFO
gym_armed_bandits.egg-info/SOURCES.txt
gym_armed_bandits.egg-info/dependency_links.txt
gym_armed_bandits.egg-info/requires.txt
gym_armed_bandits.egg-info/top_level.txt