Metadata-Version: 1.1
Name: gym-armed-bandits
Version: 0.0.1
Summary: Environvment built in OpenAI Gym for K Armed Bandits Tasks
Home-page: https://github.com/diegoalejogm/openai-k-armed-bandits
Author: Diego Gomez
Author-email: diegoalejogm@gmail.com
License: UNKNOWN
Download-URL: https://github.com/diegoalejogm/openai-k-armed-bandits/archive/0.0.1.tar.gz
Platform: UNKNOWN
